{
  "2buscontrol": {
    "page": "2buscontrol",
    "name": "2BusControl",
    "slide": "/assets/images/slides/2BC.jpg"
  },
  "drmeter": {
    "page": "drmeter",
    "name": "DRMeter",
    "slide": "/assets/images/slides/DRM.jpg"
  },
  "droffline": {
    "page": "droffline",
    "name": "DROffline",
    "slide": "/assets/images/slides/DRO.jpg"
  },
  "drm2": {
    "page": "drm2",
    "name": "DRMeter MkII",
    "slide": "/assets/images/slides/DRM2.jpg"
  },
  "dro2": {
    "page": "dro2",
    "name": "DROffline MkII",
    "slide": "/assets/images/slides/DRO2.jpg"
  },
  "theqorange": {
    "page": "theqorange",
    "name": "thEQ Orange",
    "slide": "/assets/images/slides/dummy.jpg"
  },
  "theqred": {
    "page": "theqred",
    "name": "thEQ Red",
    "slide": "/assets/images/slides/dummy.jpg"
  },
  "theqblue": {
    "page": "theqblue",
    "name": "thEQ Blue",
    "slide": "/assets/images/slides/dummy.jpg"
  },
  "rsphaseshifter": {
    "page": "rsphaseshifter",
    "name": "RSPhaseShifter",
    "slide": "/assets/images/slides/RSPS.jpg"
  }
}
